{
  "trekkid": "10000009",
  "skyldner": "22519044491",
  "opprettet": "2025-10-15T15:00:00.00Z",
  "saksnummer": "TREKK/2025/6",
  "trekkstatus": "aktiv",
  "trekkpliktig": "123456789",
  "trekkversjon": 2,
  "sekvensnummer": 290,
  "betalingsinformasjon": {
    "kidnummer": "6487719756",
    "kontonummer": "70213997155",
    "betalingsmottaker": "971648199"
  },
  "trekkstoerrelseForPeriode": [
    {
      "startdato": "2025-10-01",
      "sluttdato": "2025-10-15",
      "trekkbeloep": {
        "trekkbeloep": 8000
      }
    },
    {
      "startdato": "2025-10-16",
      "trekkbeloep": {
        "trekkbeloep": 6000
      }
    }
  ]
}